<?xml version = '1.0' encoding = 'UTF-8'?>
<Faults>
   <Fault>
      <severity>warning</severity>
      <loc>/*[namespace-uri()='http://docs.oasis-open.org/wsbpel/2.0/process/executable'][local-name()='process']</loc>
      <line>35</line>
      <col/>
      <file>BPELs/bpelGetInvoices.bpel</file>
      <name>BPELs/bpelGetInvoices.bpel</name>
      <fix>Fix the process to be *either* durable or synchronous.</fix>
      <msg>Process "bpelGetInvoices" is both durable (onMessage,Receive,Wait) and synchronous.</msg>
   </Fault>
   <Fault>
      <severity>warning</severity>
      <loc>/*[namespace-uri()='http://docs.oasis-open.org/wsbpel/2.0/process/executable'][local-name()='process']/*[namespace-uri()='http://docs.oasis-open.org/wsbpel/2.0/process/executable'][local-name()='sequence'][@name='sequenceMain']/*[namespace-uri()='http://docs.oasis-open.org/wsbpel/2.0/process/executable'][local-name()='scope'][@name='scopeGetInvoices']/*[namespace-uri()='http://docs.oasis-open.org/wsbpel/2.0/process/executable'][local-name()='sequence'][@name='sequenceGetInvoices']/*[namespace-uri()='http://docs.oasis-open.org/wsbpel/2.0/process/executable'][local-name()='if'][@name='IfRFCs']/*[namespace-uri()='http://docs.oasis-open.org/wsbpel/2.0/process/executable'][local-name()='scope'][@name='scopeGetInvoices_']/*[namespace-uri()='http://docs.oasis-open.org/wsbpel/2.0/process/executable'][local-name()='sequence'][@name='sequenceGetInvoices_']/*[namespace-uri()='http://docs.oasis-open.org/wsbpel/2.0/process/executable'][local-name()='if'][@name='IfResults']/*[namespace-uri()='http://docs.oasis-open.org/wsbpel/2.0/process/executable'][local-name()='scope'][@name='scopeDumpResults']/*[namespace-uri()='http://docs.oasis-open.org/wsbpel/2.0/process/executable'][local-name()='variables']/*[namespace-uri()='http://docs.oasis-open.org/wsbpel/2.0/process/executable'][local-name()='variable'][@name='varListZipFilesFound']</loc>
      <line>509</line>
      <col/>
      <file>BPELs/bpelGetInvoices.bpel</file>
      <name>BPELs/bpelGetInvoices.bpel</name>
      <fix>Types must be compatible.</fix>
      <msg>The from-spec of "xsd:string" is not compatible with to-spec of "ns2:ListZipFiles"</msg>
   </Fault>
   <Fault>
      <severity>warning</severity>
      <loc>/*[namespace-uri()='http://docs.oasis-open.org/wsbpel/2.0/process/executable'][local-name()='process']/*[namespace-uri()='http://docs.oasis-open.org/wsbpel/2.0/process/executable'][local-name()='sequence'][@name='sequenceMain']/*[namespace-uri()='http://docs.oasis-open.org/wsbpel/2.0/process/executable'][local-name()='scope'][@name='scopeGetInvoices']/*[namespace-uri()='http://docs.oasis-open.org/wsbpel/2.0/process/executable'][local-name()='sequence'][@name='sequenceGetInvoices']/*[namespace-uri()='http://docs.oasis-open.org/wsbpel/2.0/process/executable'][local-name()='if'][@name='IfRFCs']/*[namespace-uri()='http://docs.oasis-open.org/wsbpel/2.0/process/executable'][local-name()='scope'][@name='scopeGetInvoices_']/*[namespace-uri()='http://docs.oasis-open.org/wsbpel/2.0/process/executable'][local-name()='sequence'][@name='sequenceGetInvoices_']/*[namespace-uri()='http://docs.oasis-open.org/wsbpel/2.0/process/executable'][local-name()='if'][@name='IfResults']/*[namespace-uri()='http://docs.oasis-open.org/wsbpel/2.0/process/executable'][local-name()='scope'][@name='scopeDumpResults']/*[namespace-uri()='http://docs.oasis-open.org/wsbpel/2.0/process/executable'][local-name()='variables']/*[namespace-uri()='http://docs.oasis-open.org/wsbpel/2.0/process/executable'][local-name()='variable'][@name='varListWsErpIntegrationBizImportToErpCloudRq']</loc>
      <line>512</line>
      <col/>
      <file>BPELs/bpelGetInvoices.bpel</file>
      <name>BPELs/bpelGetInvoices.bpel</name>
      <fix>Types must be compatible.</fix>
      <msg>The from-spec of "xsd:string" is not compatible with to-spec of "ns0:ListImportToErpCloudRqType"</msg>
   </Fault>
   <Fault>
      <severity>warning</severity>
      <loc>/*[namespace-uri()='http://docs.oasis-open.org/wsbpel/2.0/process/executable'][local-name()='process']/*[namespace-uri()='http://docs.oasis-open.org/wsbpel/2.0/process/executable'][local-name()='sequence'][@name='sequenceMain']/*[namespace-uri()='http://docs.oasis-open.org/wsbpel/2.0/process/executable'][local-name()='scope'][@name='scopeGetInvoices']/*[namespace-uri()='http://docs.oasis-open.org/wsbpel/2.0/process/executable'][local-name()='sequence'][@name='sequenceGetInvoices']/*[namespace-uri()='http://docs.oasis-open.org/wsbpel/2.0/process/executable'][local-name()='if'][@name='IfRFCs']/*[namespace-uri()='http://docs.oasis-open.org/wsbpel/2.0/process/executable'][local-name()='scope'][@name='scopeGetInvoices_']/*[namespace-uri()='http://docs.oasis-open.org/wsbpel/2.0/process/executable'][local-name()='sequence'][@name='sequenceGetInvoices_']/*[namespace-uri()='http://docs.oasis-open.org/wsbpel/2.0/process/executable'][local-name()='if'][@name='IfResults']/*[namespace-uri()='http://docs.oasis-open.org/wsbpel/2.0/process/executable'][local-name()='scope'][@name='scopeDumpResults']/*[namespace-uri()='http://docs.oasis-open.org/wsbpel/2.0/process/executable'][local-name()='variables']/*[namespace-uri()='http://docs.oasis-open.org/wsbpel/2.0/process/executable'][local-name()='variable'][@name='varListBUsFound']</loc>
      <line>515</line>
      <col/>
      <file>BPELs/bpelGetInvoices.bpel</file>
      <name>BPELs/bpelGetInvoices.bpel</name>
      <fix>Types must be compatible.</fix>
      <msg>The from-spec of "xsd:string" is not compatible with to-spec of "ns2:ListBusAndOrgId"</msg>
   </Fault>
   <Fault>
      <severity>warning</severity>
      <loc>/*[namespace-uri()='http://docs.oasis-open.org/wsbpel/2.0/process/executable'][local-name()='process']/*[namespace-uri()='http://docs.oasis-open.org/wsbpel/2.0/process/executable'][local-name()='sequence'][@name='sequenceMain']/*[namespace-uri()='http://docs.oasis-open.org/wsbpel/2.0/process/executable'][local-name()='scope'][@name='scopeGetInvoices']/*[namespace-uri()='http://docs.oasis-open.org/wsbpel/2.0/process/executable'][local-name()='sequence'][@name='sequenceGetInvoices']/*[namespace-uri()='http://docs.oasis-open.org/wsbpel/2.0/process/executable'][local-name()='if'][@name='IfRFCs']/*[namespace-uri()='http://docs.oasis-open.org/wsbpel/2.0/process/executable'][local-name()='scope'][@name='scopeGetInvoices_']/*[namespace-uri()='http://docs.oasis-open.org/wsbpel/2.0/process/executable'][local-name()='sequence'][@name='sequenceGetInvoices_']/*[namespace-uri()='http://docs.oasis-open.org/wsbpel/2.0/process/executable'][local-name()='if'][@name='IfResults']/*[namespace-uri()='http://docs.oasis-open.org/wsbpel/2.0/process/executable'][local-name()='scope'][@name='scopeDumpResults']/*[namespace-uri()='http://docs.oasis-open.org/wsbpel/2.0/process/executable'][local-name()='sequence'][@name='sequenceDumpResults']/*[namespace-uri()='http://docs.oasis-open.org/wsbpel/2.0/process/executable'][local-name()='if'][@name='IfFoundTrxNbr']/*[namespace-uri()='http://docs.oasis-open.org/wsbpel/2.0/process/executable'][local-name()='scope'][@name='scopeFoundTrxNbr']/*[namespace-uri()='http://docs.oasis-open.org/wsbpel/2.0/process/executable'][local-name()='variables']/*[namespace-uri()='http://docs.oasis-open.org/wsbpel/2.0/process/executable'][local-name()='variable'][@name='varBatchId']</loc>
      <line>566</line>
      <col/>
      <file>BPELs/bpelGetInvoices.bpel</file>
      <name>BPELs/bpelGetInvoices.bpel</name>
      <fix>Types must be compatible.</fix>
      <msg>The from-spec of "xsd:string" is not compatible with to-spec of "ns2:StringHelper"</msg>
   </Fault>
   <Fault>
      <severity>warning</severity>
      <loc>/*[namespace-uri()='http://docs.oasis-open.org/wsbpel/2.0/process/executable'][local-name()='process']/*[namespace-uri()='http://docs.oasis-open.org/wsbpel/2.0/process/executable'][local-name()='sequence'][@name='sequenceMain']/*[namespace-uri()='http://docs.oasis-open.org/wsbpel/2.0/process/executable'][local-name()='scope'][@name='scopeGetInvoices']/*[namespace-uri()='http://docs.oasis-open.org/wsbpel/2.0/process/executable'][local-name()='sequence'][@name='sequenceGetInvoices']/*[namespace-uri()='http://docs.oasis-open.org/wsbpel/2.0/process/executable'][local-name()='if'][@name='IfRFCs']/*[namespace-uri()='http://docs.oasis-open.org/wsbpel/2.0/process/executable'][local-name()='scope'][@name='scopeGetInvoices_']/*[namespace-uri()='http://docs.oasis-open.org/wsbpel/2.0/process/executable'][local-name()='sequence'][@name='sequenceGetInvoices_']/*[namespace-uri()='http://docs.oasis-open.org/wsbpel/2.0/process/executable'][local-name()='if'][@name='IfResults']/*[namespace-uri()='http://docs.oasis-open.org/wsbpel/2.0/process/executable'][local-name()='scope'][@name='scopeDumpResults']/*[namespace-uri()='http://docs.oasis-open.org/wsbpel/2.0/process/executable'][local-name()='sequence'][@name='sequenceDumpResults']/*[namespace-uri()='http://docs.oasis-open.org/wsbpel/2.0/process/executable'][local-name()='if'][@name='IfFoundTrxNbr']/*[namespace-uri()='http://docs.oasis-open.org/wsbpel/2.0/process/executable'][local-name()='scope'][@name='scopeFoundTrxNbr']/*[namespace-uri()='http://docs.oasis-open.org/wsbpel/2.0/process/executable'][local-name()='sequence'][@name='sequenceFoundTrxNbr']/*[namespace-uri()='http://docs.oasis-open.org/wsbpel/2.0/process/executable'][local-name()='forEach'][@name='ForEachListZipF']/*[namespace-uri()='http://docs.oasis-open.org/wsbpel/2.0/process/executable'][local-name()='scope'][@name='scopeForEachListZipF']/*[namespace-uri()='http://docs.oasis-open.org/wsbpel/2.0/process/executable'][local-name()='sequence'][@name='sequenceForEachListZipF']/*[namespace-uri()='http://docs.oasis-open.org/wsbpel/2.0/process/executable'][local-name()='assign'][@name='assignListZipFileAux']/*[namespace-uri()='http://docs.oasis-open.org/wsbpel/2.0/process/executable'][local-name()='copy'][2]</loc>
      <line>624</line>
      <col/>
      <file>BPELs/bpelGetInvoices.bpel</file>
      <name>BPELs/bpelGetInvoices.bpel</name>
      <fix>Types must be compatible.</fix>
      <msg>The from-spec of "ns1:FileType" is not compatible with to-spec of "ns0:FileType"</msg>
   </Fault>
   <Fault>
      <severity>warning</severity>
      <loc>/*[namespace-uri()='http://docs.oasis-open.org/wsbpel/2.0/process/executable'][local-name()='process']/*[namespace-uri()='http://docs.oasis-open.org/wsbpel/2.0/process/executable'][local-name()='sequence'][@name='main']/*[namespace-uri()='http://docs.oasis-open.org/wsbpel/2.0/process/executable'][local-name()='if'][@name='IfErrorsGenerateReport']/*[namespace-uri()='http://docs.oasis-open.org/wsbpel/2.0/process/executable'][local-name()='condition']</loc>
      <line>117</line>
      <col/>
      <file>BPELs/bpelElecInvoice.bpel</file>
      <name>BPELs/bpelElecInvoice.bpel</name>
      <fix>Make sure that the expression in &lt;bpel:condition> is a boolean expression.</fix>
      <msg>The expression $varInvokeWsERPIntegrationBizGenerateReportRs.Ge ... in &lt;bpel:condition> is not a boolean expression.</msg>
   </Fault>
   <Fault>
      <severity>warning</severity>
      <loc>/*[namespace-uri()='http://docs.oasis-open.org/wsbpel/2.0/process/executable'][local-name()='process']/*[namespace-uri()='http://docs.oasis-open.org/wsbpel/2.0/process/executable'][local-name()='sequence'][@name='main']/*[namespace-uri()='http://docs.oasis-open.org/wsbpel/2.0/process/executable'][local-name()='if'][@name='IfErrorsGenerateReport']/*[namespace-uri()='http://docs.oasis-open.org/wsbpel/2.0/process/executable'][local-name()='assign'][@name='assigErrorGenerateReport']/*[namespace-uri()='http://docs.oasis-open.org/wsbpel/2.0/process/executable'][local-name()='copy']</loc>
      <line>124</line>
      <col/>
      <file>BPELs/bpelElecInvoice.bpel</file>
      <name>BPELs/bpelElecInvoice.bpel</name>
      <fix>Types must be compatible.</fix>
      <msg>The from-spec of "ns2:ErrorsType" is not compatible with to-spec of "ns2:ErrorType"</msg>
   </Fault>
   <Fault>
      <severity>warning</severity>
      <loc>/*[namespace-uri()='http://docs.oasis-open.org/wsbpel/2.0/process/executable'][local-name()='process']/*[namespace-uri()='http://docs.oasis-open.org/wsbpel/2.0/process/executable'][local-name()='sequence'][@name='sequenceBpelLoadInvoices']/*[namespace-uri()='http://docs.oasis-open.org/wsbpel/2.0/process/executable'][local-name()='if'][@name='IfInvoicesToLoad']/*[namespace-uri()='http://docs.oasis-open.org/wsbpel/2.0/process/executable'][local-name()='scope'][@name='scopeIfInvoicesToLoad']/*[namespace-uri()='http://docs.oasis-open.org/wsbpel/2.0/process/executable'][local-name()='variables']/*[namespace-uri()='http://docs.oasis-open.org/wsbpel/2.0/process/executable'][local-name()='variable'][@name='varParamsToGetOrgId']</loc>
      <line>102</line>
      <col/>
      <file>BPELs/bpelLoadInvoices.bpel</file>
      <name>BPELs/bpelLoadInvoices.bpel</name>
      <fix>Types must be compatible.</fix>
      <msg>The from-spec of "xsd:string" is not compatible with to-spec of "ns3:ParamsToGetOrgId"</msg>
   </Fault>
   <Fault>
      <severity>warning</severity>
      <loc>/*[namespace-uri()='http://docs.oasis-open.org/wsbpel/2.0/process/executable'][local-name()='process']/*[namespace-uri()='http://docs.oasis-open.org/wsbpel/2.0/process/executable'][local-name()='sequence'][@name='sequenceBpelLoadInvoices']/*[namespace-uri()='http://docs.oasis-open.org/wsbpel/2.0/process/executable'][local-name()='if'][@name='IfInvoicesToLoad']/*[namespace-uri()='http://docs.oasis-open.org/wsbpel/2.0/process/executable'][local-name()='scope'][@name='scopeIfInvoicesToLoad']/*[namespace-uri()='http://docs.oasis-open.org/wsbpel/2.0/process/executable'][local-name()='variables']/*[namespace-uri()='http://docs.oasis-open.org/wsbpel/2.0/process/executable'][local-name()='variable'][@name='varParamsToUpdateInvoices']</loc>
      <line>105</line>
      <col/>
      <file>BPELs/bpelLoadInvoices.bpel</file>
      <name>BPELs/bpelLoadInvoices.bpel</name>
      <fix>Types must be compatible.</fix>
      <msg>The from-spec of "xsd:string" is not compatible with to-spec of "ns3:ParamsToUpdateStatusInvoicesToBD"</msg>
   </Fault>
   <Fault>
      <severity>warning</severity>
      <loc>/*[namespace-uri()='http://docs.oasis-open.org/wsbpel/2.0/process/executable'][local-name()='process']/*[namespace-uri()='http://docs.oasis-open.org/wsbpel/2.0/process/executable'][local-name()='sequence'][@name='sequenceBpelLoadInvoices']/*[namespace-uri()='http://docs.oasis-open.org/wsbpel/2.0/process/executable'][local-name()='if'][@name='IfInvoicesToLoad']/*[namespace-uri()='http://docs.oasis-open.org/wsbpel/2.0/process/executable'][local-name()='scope'][@name='scopeIfInvoicesToLoad']/*[namespace-uri()='http://docs.oasis-open.org/wsbpel/2.0/process/executable'][local-name()='sequence'][@name='sequenceIfInvoicesToLoad']/*[namespace-uri()='http://docs.oasis-open.org/wsbpel/2.0/process/executable'][local-name()='scope'][@name='scopeNotifyLoadInvoices']/*[namespace-uri()='http://docs.oasis-open.org/wsbpel/2.0/process/executable'][local-name()='sequence'][@name='sequenceNotifyLoadInvoices']/*[namespace-uri()='http://docs.oasis-open.org/wsbpel/2.0/process/executable'][local-name()='if'][@name='IfActivateFlowUpdUuid']/*[namespace-uri()='http://docs.oasis-open.org/wsbpel/2.0/process/executable'][local-name()='scope'][@name='scopePickWaitForLoadInvoices']/*[namespace-uri()='http://docs.oasis-open.org/wsbpel/2.0/process/executable'][local-name()='sequence'][@name='sequencePickWaitForLoadInvoices']/*[namespace-uri()='http://docs.oasis-open.org/wsbpel/2.0/process/executable'][local-name()='if'][@name='IfResultsDm']/*[namespace-uri()='http://docs.oasis-open.org/wsbpel/2.0/process/executable'][local-name()='scope'][@name='scopeIfResultsDm']/*[namespace-uri()='http://docs.oasis-open.org/wsbpel/2.0/process/executable'][local-name()='variables']/*[namespace-uri()='http://docs.oasis-open.org/wsbpel/2.0/process/executable'][local-name()='variable'][@name='varTrxNumberOrgIdAndUuId']</loc>
      <line>296</line>
      <col/>
      <file>BPELs/bpelLoadInvoices.bpel</file>
      <name>BPELs/bpelLoadInvoices.bpel</name>
      <fix>Types must be compatible.</fix>
      <msg>The from-spec of "xsd:string" is not compatible with to-spec of "ns3:ParamsToUpdateUuid"</msg>
   </Fault>
   <Fault>
      <severity>warning</severity>
      <loc>/*[namespace-uri()='http://docs.oasis-open.org/wsbpel/2.0/process/executable'][local-name()='process']/*[namespace-uri()='http://docs.oasis-open.org/wsbpel/2.0/process/executable'][local-name()='sequence'][@name='sequenceBpelLoadInvoices']/*[namespace-uri()='http://docs.oasis-open.org/wsbpel/2.0/process/executable'][local-name()='if'][@name='IfInvoicesToLoad']/*[namespace-uri()='http://docs.oasis-open.org/wsbpel/2.0/process/executable'][local-name()='scope'][@name='scopeIfInvoicesToLoad']/*[namespace-uri()='http://docs.oasis-open.org/wsbpel/2.0/process/executable'][local-name()='sequence'][@name='sequenceIfInvoicesToLoad']/*[namespace-uri()='http://docs.oasis-open.org/wsbpel/2.0/process/executable'][local-name()='scope'][@name='scopeNotifyLoadInvoices']/*[namespace-uri()='http://docs.oasis-open.org/wsbpel/2.0/process/executable'][local-name()='sequence'][@name='sequenceNotifyLoadInvoices']/*[namespace-uri()='http://docs.oasis-open.org/wsbpel/2.0/process/executable'][local-name()='if'][@name='IfActivateFlowUpdUuid']/*[namespace-uri()='http://docs.oasis-open.org/wsbpel/2.0/process/executable'][local-name()='scope'][@name='scopePickWaitForLoadInvoices']/*[namespace-uri()='http://docs.oasis-open.org/wsbpel/2.0/process/executable'][local-name()='sequence'][@name='sequencePickWaitForLoadInvoices']/*[namespace-uri()='http://docs.oasis-open.org/wsbpel/2.0/process/executable'][local-name()='if'][@name='IfResultsDm']/*[namespace-uri()='http://docs.oasis-open.org/wsbpel/2.0/process/executable'][local-name()='scope'][@name='scopeIfResultsDm']/*[namespace-uri()='http://docs.oasis-open.org/wsbpel/2.0/process/executable'][local-name()='variables']/*[namespace-uri()='http://docs.oasis-open.org/wsbpel/2.0/process/executable'][local-name()='variable'][@name='varParamsToGenerateReportCustTrxId']</loc>
      <line>300</line>
      <col/>
      <file>BPELs/bpelLoadInvoices.bpel</file>
      <name>BPELs/bpelLoadInvoices.bpel</name>
      <fix>Types must be compatible.</fix>
      <msg>The from-spec of "xsd:string" is not compatible with to-spec of "ns3:ParamsToGenerateReport"</msg>
   </Fault>
</Faults>
